MANIFEST.in
README.md
requirements.txt
setup.py
dynastes/__init__.py
dynastes.egg-info/PKG-INFO
dynastes.egg-info/SOURCES.txt
dynastes.egg-info/dependency_links.txt
dynastes.egg-info/top_level.txt
dynastes/activations/__init__.py
dynastes/blocks/__init__.py
dynastes/blocks/attention_blocks.py
dynastes/blocks/causal_blocks.py
dynastes/blocks/layer_factory.py
dynastes/blocks/transformer_blocks.py
dynastes/core/__init__.py
dynastes/core/backend.py
dynastes/core/nn/__init__.py
dynastes/core/nn/array_ops.py
dynastes/core/nn/grad_helpers.py
dynastes/core/nn/math_ops.py
dynastes/core/nn/nn_ops.py
dynastes/data_augmentation/__init__.py
dynastes/data_augmentation/audio_spectrum.py
dynastes/helpers/__init__.py
dynastes/helpers/hyperparameters/__init__.py
dynastes/helpers/hyperparameters/efficientnet.py
dynastes/layers/__init__.py
dynastes/layers/attention_layers.py
dynastes/layers/base_layers.py
dynastes/layers/conditioning_layers.py
dynastes/layers/convolutional_layers.py
dynastes/layers/data_augmentation.py
dynastes/layers/gating_layers.py
dynastes/layers/normalization_layers.py
dynastes/layers/random_layers.py
dynastes/layers/spectral_layers.py
dynastes/layers/t2t_attention_layers.py
dynastes/layers/time_delay_layers.py
dynastes/layers/transformer_layers.py
dynastes/models/__init__.py
dynastes/models/growing_gan_models.py
dynastes/ops/__init__.py
dynastes/ops/attention_nd.py
dynastes/ops/embedding_ops.py
dynastes/ops/image_ops.py
dynastes/ops/localized_attention_nd.py
dynastes/ops/pad_ops.py
dynastes/ops/scale_ops.py
dynastes/ops/spectral_ops.py
dynastes/ops/t2t_attention.py
dynastes/ops/t2t_common.py
dynastes/ops/time_delay_ops.py
dynastes/probability/__init__.py
dynastes/probability/bijector_partials.py
dynastes/probability/bijectors.py
dynastes/probability/pseudoblocksparse_bijectors.py
dynastes/regularizers/__init__.py
dynastes/regularizers/orthogonal.py
dynastes/util/__init__.py
dynastes/util/cache_context.py
dynastes/util/layer_util.py
dynastes/util/precision_util.py
dynastes/util/t2t_expert_util.py
dynastes/util/test_utils.py
dynastes/weight_normalizers/__init__.py
