Metadata-Version: 2.1
Name: dynastes
Version: 0.9.3
Summary: A collection of layers and utils for TensorFlow (Keras) 2.+
Home-page: https://github.com/dynastes-team/dynastes
Author: Team Dynastes
Author-email: v3qt0r@gmail.com
License: UNKNOWN
Platform: UNKNOWN
Classifier: Development Status :: 3 - Alpha
Classifier: Programming Language :: Python :: 3
Classifier: License :: OSI Approved :: MIT License
Classifier: Operating System :: OS Independent
Requires-Python: >=3.6
